rnnoisepy/__init__.py
rnnoisepy/rnnoise.py
rnnoisepy/lib/COPYING.librnnoise
rnnoisepy/lib/librnnoise.so
rnnoisepy/lib/librnnoise.so.0
rnnoisepy/lib/librnnoise.so.0.4.1
rnnoisepy-1.0.0.dist-info/METADATA
rnnoisepy-1.0.0.dist-info/WHEEL
rnnoisepy-1.0.0.dist-info/RECORD
rnnoisepy-1.0.0.dist-info/licenses/LICENSE
