Metadata-Version: 2.4
Name: rnnoisepy
Version: 1.0.0
Summary: RNNoise(python bindings)
Author-email: Akito Miura <phenomer@g.hachune.net>
License: BSD-3-Clause
License-File: LICENSE
Classifier: License :: OSI Approved :: BSD License
Classifier: Operating System :: POSIX :: Linux
Classifier: Programming Language :: Python :: 3
Requires-Python: >=3.12
Requires-Dist: numpy>=1.26.4
